matrix_package_krp
