Metadata-Version: 1.0
Name: matrix-package-krp
Version: 0.4
Summary: Basic Matrix Operations
Home-page: UNKNOWN
Author: UNKNOWN
Author-email: UNKNOWN
License: UNKNOWN
Platform: UNKNOWN
